_pyspng_c.cpython-310-darwin.so
pyspng/__init__.py
pyspng_cli/__init__.py
pyspng_cli/cli.py
pyspng_seunglab-1.1.2.dist-info/RECORD
pyspng_seunglab-1.1.2.dist-info/LICENSE
pyspng_seunglab-1.1.2.dist-info/WHEEL
pyspng_seunglab-1.1.2.dist-info/entry_points.txt
pyspng_seunglab-1.1.2.dist-info/top_level.txt
pyspng_seunglab-1.1.2.dist-info/METADATA
