Metadata-Version: 2.2
Name: pyspng-seunglab
Version: 1.1.2
Summary: Fast libspng-based PNG decoder. Fork of pyspng.
Home-page: https://github.com/seung-lab/pyspng-seunglab
Author: William Silversmith (this fork), Janne Hellsten (original)
Author-email: ws9@princeton.edu, jjhellst@gmail.com
Project-URL: Tracker, https://github.com/seung-lab/pyspng-seunglab
Classifier: Intended Audience :: Developers
Classifier: Development Status :: 4 - Beta
Classifier: Programming Language :: Python
Classifier: Programming Language :: Python :: 3
Classifier: Programming Language :: Python :: 3.8
Classifier: Programming Language :: Python :: 3.9
Classifier: Programming Language :: Python :: 3.10
Classifier: Programming Language :: Python :: 3.11
Classifier: Programming Language :: Python :: 3.12
Classifier: Operating System :: POSIX
Classifier: Operating System :: MacOS
Classifier: Operating System :: Microsoft :: Windows :: Windows 10
Classifier: Topic :: Scientific/Engineering :: Image Processing
Classifier: Topic :: System :: Archiving :: Compression
License-File: LICENSE
Requires-Dist: numpy
Provides-Extra: test
Requires-Dist: pytest; extra == "test"
Dynamic: author
Dynamic: author-email
Dynamic: classifier
Dynamic: description
Dynamic: description-content-type
Dynamic: home-page
Dynamic: project-url
Dynamic: provides-extra
Dynamic: requires-dist
Dynamic: summary
